semverkit/__init__.py
semverkit/__main__.py
semverkit/core.py
semverkit-1.1.0.dist-info/LICENSE
semverkit-1.1.0.dist-info/METADATA
semverkit-1.1.0.dist-info/WHEEL
semverkit-1.1.0.dist-info/entry_points.txt
semverkit-1.1.0.dist-info/top_level.txt
semverkit-1.1.0.dist-info/RECORD
