Metadata-Version: 2.1
Name: semverkit
Version: 1.1.0
Summary: Semantic Versioning CLI
Author-email: Elmer Nocon <elmernocon@gmail.com>
License: MIT License
Classifier: Intended Audience :: Developers
Classifier: License :: OSI Approved :: MIT License
Classifier: Operating System :: OS Independent
Classifier: Programming Language :: Python
Classifier: Programming Language :: Python :: 3.9
Classifier: Programming Language :: Python :: 3.10
Classifier: Programming Language :: Python :: 3.11
Classifier: Programming Language :: Python :: 3.12
Requires-Python: >=3.9
License-File: LICENSE
Requires-Dist: click ==8.1.7
Requires-Dist: semver ==3.0.2
Provides-Extra: dev
Requires-Dist: ruff ; extra == 'dev'
